ftcbz/__init__.py
ftcbz/ftcbz.py
ftcbz-2.3.2.dist-info/DESCRIPTION.rst
ftcbz-2.3.2.dist-info/METADATA
ftcbz-2.3.2.dist-info/RECORD
ftcbz-2.3.2.dist-info/WHEEL
ftcbz-2.3.2.dist-info/entry_points.txt
ftcbz-2.3.2.dist-info/metadata.json
ftcbz-2.3.2.dist-info/top_level.txt
