Metadata-Version: 2.0
Name: ftcbz
Version: 2.3.2
Summary: A script to archive multiple comic book dir to .cbz format
Home-page: https://bitbucket.org/civalin/ftcbz
Author: Civa Lin
Author-email: larinawf@gmail.com
License: MIT
Keywords: cbz comic archive
Platform: UNKNOWN
Classifier: Programming Language :: Python :: 3
Classifier: Topic :: Multimedia :: Graphics :: Graphics Conversion
Classifier: Topic :: System :: Archiving
